{"https://co.linkedin.com/in/myriam-julieth-contreras-gelves-ingindustrial?original_referer=https%3A%2F%2Fwww.google.com%2F":{"error":false,"response":{"first_name":"Myriam Julieth","last_name":"Contreras Gelves","full_name":"Myriam Julieth Contreras Gelves","gender":"female","job_title":"Ingeniera Industrial","linkedin":"https://www.linkedin.com/in/myriam-julieth-contreras-gelves-ingindustrial","summary":null,"premium":false,"skills":null,"work_experience":[{"company":{"id":null,"name":null,"logo":null,"url":null,"employees":{"start":null,"end":null}},"date":{"start":{"month":null,"day":null,"year":null},"end":{"month":null,"day":null,"year":null}},"profile_positions":[{"location":null,"date":{"start":{"month":null,"day":null,"year":null},"end":{"month":null,"day":null,"year":null}},"company":null,"description":null,"title":"Ingeniero de asuntos de calidad","employment_type":"Freelance"}]}],"education":[],"languages":{"primary_locale":{"country":"ES","language":"es"},"supported_locales":[{"country":"ES","language":"es"}],"profile_languages":[]},"current_job_year":null,"current_job_month":null,"picture":"https://assets-prospeo.s3.us-east-2.amazonaws.com/lead_6HPPSXDM3H0C8U79NNJ9.jpg","email":{"email":null,"email_anon_id":null,"email_status":"NOT_FOUND","email_type":"professional"},"company":{"name":null},"location":{"country":"Colombia","country_code":"PH","state":"Capital District","city":"Valenzuela","timezone":"Asia/Manila","timezone_offset":8.0,"postal_code":"0550","raw":"Capital District, Colombia"}}}}