{"https://co.linkedin.com/in/manuel-alejandro-montero-suarez-a63670173":{"error":false,"response":{"first_name":"Manuel Alejandro","last_name":"Montero Suarez","full_name":"Manuel Alejandro Montero Suarez","gender":"male","job_title":"Director t\u00e9cnico en Monterra SAS","linkedin":"https://www.linkedin.com/in/manuel-alejandro-montero-suarez-a63670173","summary":null,"premium":false,"skills":null,"work_experience":[{"company":{"id":null,"name":"Monterra SAS","logo":null,"url":null,"employees":{"start":null,"end":null}},"date":{"start":{"month":null,"day":null,"year":null},"end":{"month":null,"day":null,"year":null}},"profile_positions":[{"location":null,"date":{"start":{"month":null,"day":null,"year":null},"end":{"month":null,"day":null,"year":null}},"company":"Monterra SAS","description":null,"title":"Director t\u00e9cnico","employment_type":null}]}],"education":[],"languages":{"primary_locale":{"country":"ES","language":"es"},"supported_locales":[{"country":"ES","language":"es"}],"profile_languages":[]},"current_job_year":null,"current_job_month":null,"picture":null,"email":{"email":null,"email_anon_id":null,"email_status":"NOT_FOUND","email_type":"professional"},"company":{"name":"Monterra SAS"},"location":{"country":"Colombia","country_code":"CO","state":null,"city":"Bogota","timezone":"America/Bogota","timezone_offset":-5.0,"postal_code":null,"raw":"Bogota, D.C., Capital District, Colombia"}}}}