{"https://co.linkedin.com/in/jose-fabian-diaz-botiva-93244520b":{"error":false,"response":{"first_name":"Jose Fabian","last_name":"Diaz Botiva","full_name":"JOSE FABIAN DIAZ BOTIVA ","gender":"male","job_title":"Auxiliar administrativo en Aforos y encomiendas ltda","linkedin":"https://www.linkedin.com/in/jose-fabian-diaz-botiva-93244520b","summary":null,"premium":false,"skills":null,"work_experience":[{"company":{"id":null,"name":"Aforos y encomiendas ltda","logo":null,"url":null,"employees":{"start":null,"end":null}},"date":{"start":{"month":5,"day":null,"year":2014},"end":{"month":null,"day":null,"year":null}},"profile_positions":[{"location":null,"date":{"start":{"month":5,"day":null,"year":2014},"end":{"month":null,"day":null,"year":null}},"company":"Aforos y encomiendas ltda","description":null,"title":"Auxiliar administrativo","employment_type":"Full-time"}]},{"company":{"id":1790344,"name":"Agropecuaria Aliar S.A.","logo":"https://media.licdn.com/dms/image/C4E0BAQHx-bdF6H6igA/company-logo_400_400/0/1623427097776/agropecuaria_aliar_sa_logo?e=1705536000&v=beta&t=BWxxvhCXSvtaJmJUdJbHVQJnMIqjV32C594OFYR6skE","url":"https://www.linkedin.com/company/agropecuaria-aliar-s.a./","employees":{"start":1001,"end":5000}},"date":{"start":{"month":2,"day":null,"year":2020},"end":{"month":8,"day":null,"year":2020}},"profile_positions":[{"location":null,"date":{"start":{"month":2,"day":null,"year":2020},"end":{"month":8,"day":null,"year":2020}},"company":"Agropecuaria Aliar S.A.","description":"Asistente t\u00e9cnico en el dise\u00f1o de sistemas de riego y construcciones rurales","title":"Asistente t\u00e9cnico","employment_type":"Full-time"}]}],"education":[],"languages":{"primary_locale":{"country":"ES","language":"es"},"supported_locales":[{"country":"ES","language":"es"}],"profile_languages":[]},"current_job_year":2014,"current_job_month":5,"picture":null,"email":{"email":null,"email_anon_id":null,"email_status":"NOT_FOUND","email_type":"professional"},"company":{"name":"Aforos y encomiendas ltda"},"location":{"country":"Colombia","country_code":"CO","state":null,"city":"Bogota","timezone":"America/Bogota","timezone_offset":-5.0,"postal_code":null,"raw":"Bogota, D.C., Capital District, Colombia"}}}}