{"https://co.linkedin.com/in/arley-yecid-morcote-arleymorcote-814592179":{"error":false,"response":{"first_name":"Arley Yecid Morcote","last_name":"Arleymorcote","full_name":"Arley yecid morcote arleymorcote","gender":"male","job_title":"Gerente de gesti\u00f3n en AM ELECTRIC","linkedin":"https://www.linkedin.com/in/arley-yecid-morcote-arleymorcote-814592179","summary":null,"premium":false,"skills":null,"work_experience":[{"company":{"id":15519158,"name":"AM ELECTRIC","logo":null,"url":"https://www.linkedin.com/company/am-electric/","employees":{"start":2,"end":10}},"date":{"start":{"month":null,"day":null,"year":null},"end":{"month":null,"day":null,"year":null}},"profile_positions":[{"location":null,"date":{"start":{"month":null,"day":null,"year":null},"end":{"month":null,"day":null,"year":null}},"company":"AM ELECTRIC","description":null,"title":"Gerente de gesti\u00f3n","employment_type":null}]}],"education":[],"languages":{"primary_locale":{"country":"ES","language":"es"},"supported_locales":[{"country":"ES","language":"es"}],"profile_languages":[]},"current_job_year":null,"current_job_month":null,"picture":"https://assets-prospeo.s3.us-east-2.amazonaws.com/lead_0KA0NR10F68VZWYV79M8.jpg","email":{"email":null,"email_anon_id":null,"email_status":"NOT_FOUND","email_type":"professional"},"company":{"name":"AM ELECTRIC","is_catch_all":null,"size":"2-10","logo":"https://logo.clearbit.com/amelectricltd.com","linkedin":"https://www.linkedin.com/company/am-electric","website":"http://amelectricltd.com","domain":"amelectricltd.com","common_email_pattern":null,"industry":"","founded_in":null,"description":"AM ELECTRIC is a company based out of 568 WATERFORD LN, VALPARAISO, Indiana, United States.","total_emails":2,"location":{"country":"United States","country_code":"US","state":null,"city":"Valparaiso","timezone":"America/New_York","timezone_offset":"-4.0","postal_code":null,"address":null}},"location":{"country":"Colombia","country_code":"CO","state":null,"city":"Bogota","timezone":"America/Bogota","timezone_offset":-5.0,"postal_code":null,"raw":"Bogota, D.C., Capital District, Colombia"}}}}