{"https://co.linkedin.com/in/david-stiven-gonzalez-hernandez-bba487186":{"error":false,"response":{"first_name":"David Stiven","last_name":"Gonzalez Hernandez","full_name":"David Stiven Gonzalez Hernandez","gender":"male","job_title":"Ingenier\u00eda Civil","linkedin":"https://www.linkedin.com/in/david-stiven-gonzalez-hernandez-bba487186","summary":null,"premium":false,"skills":null,"work_experience":[{"company":{"id":6868399,"name":"INGEMA S.A.","logo":"https://media.licdn.com/dms/image/C4D0BAQGM1cQAUDr1xQ/company-logo_400_400/0/1543534567892?e=1705536000&v=beta&t=Uy5MTe5z7h6_Ogkf60zw3q6xhS2RehNwTm_ZGGdjYUs","url":"https://www.linkedin.com/company/ingema-sa/","employees":{"start":501,"end":1000}},"date":{"start":{"month":4,"day":null,"year":2021},"end":{"month":4,"day":null,"year":2022}},"profile_positions":[{"location":"Bogot\u00e1, Distrito Capital, Colombia","date":{"start":{"month":4,"day":null,"year":2021},"end":{"month":4,"day":null,"year":2022}},"company":"INGEMA S.A.","description":null,"title":"Controller de proyectos","employment_type":"Full-time"}]}],"education":[{"date":{"start":{"month":null,"day":null,"year":2015},"end":{"month":null,"day":null,"year":2020}},"school":{"name":"Universidad Cat\u00f3lica de Colombia","logo":null,"url":"https://www.linkedin.com/school/universidad-catolica-de-colombia/"},"degree_name":"Ingenieria ","field_of_study":"Ingenier\u00eda civil","grade":null}],"languages":{"primary_locale":{"country":"ES","language":"es"},"supported_locales":[{"country":"ES","language":"es"}],"profile_languages":[]},"current_job_year":2021,"current_job_month":4,"picture":null,"email":{"email":null,"email_anon_id":null,"email_status":"NOT_FOUND","email_type":"professional"},"company":{"name":"INGEMA S.A.","is_catch_all":null,"size":"501-1000","logo":"https://assets-prospeo.s3.us-east-2.amazonaws.com/company_HODWDR1YKV52TE2YHPL5.jpg","linkedin":"https://www.linkedin.com/company/ingema-sa","website":"http://ingema-sa.com.co","domain":"ingema-sa.com.co","common_email_pattern":null,"industry":"Utilities","founded_in":2003,"description":"En INGEMA S.A. desarrollamos proyectos de ingenier\u00eda e infraestructura brindando soluciones innovadoras y satisfaciendo los requerimientos de nuestros clientes; vinculando colaboradores altamente competentes, contribuyendo y comprometidos con nuestra organizaci\u00f3n.\n\nNos esforzamos cada d\u00eda por desarrollar programas integrales que protejan la seguridad y la salud de los trabajadores independiente de su forma de contrataci\u00f3n, para  prevenir lesiones y enfermedades laborales, a trav\u00e9s de la identificaic\u00f3n de los peligors, evaluaci\u00f3n y valoraci\u00f3n de los riesgos, y el cumplimiento de la legislaci\u00f3n vigente.\n\n Apoyo en la compra de productos y servicios que maximizan la relaci\u00f3n eficiencia energ\u00eda y el dise\u00f1o de elementos que permitan mejorar el desempe\u00f1o energ\u00e9tico, incluyendo el compromiso de disponibilidad de la informaci\u00f3n y recursos necesarios, el bienestar de nuestros colaboradores y la prevenci\u00f3n de la contaminaci\u00f3n mediante el uso eficiente de los recursos naturales, la energ\u00eda y su consumo.\n\nEn INGEMA S.A. estamos convencidos que a trav\u00e9s del mejoramiento continuo de los procesos y sistemas se alcanza un nivel sobresaliente aumentando el posicionamiento en el mercado, y asegurando la rentabilidad de la compa\u00f1\u00eda. ","total_emails":2,"location":{"country":"Colombia","country_code":"CO","state":null,"city":"Medell\u00edn","timezone":"America/Bogota","timezone_offset":"-5.0","postal_code":null,"address":"Carrera 43 A N\u00ba 14 - 57"}},"location":{"country":null,"country_code":null,"state":null,"city":null,"timezone":null,"timezone_offset":null,"postal_code":null,"raw":"Bogota, D.C., Capital District, Colombia"}}}}